textgrids/__init__.py
textgrids/templates.py
textgrids/transcript.py
praat_textgrids-1.4.0.dist-info/LICENSE
praat_textgrids-1.4.0.dist-info/METADATA
praat_textgrids-1.4.0.dist-info/WHEEL
praat_textgrids-1.4.0.dist-info/top_level.txt
praat_textgrids-1.4.0.dist-info/RECORD
