Metadata-Version: 2.1
Name: praat-textgrids
Version: 1.4.0
Summary: Manipulation of Praat TextGrids
Home-page: http://github.com/Legisign/Praat-textgrids
Author: Legisign.org
Author-email: software@legisign.org
License: GPLv3
License-File: LICENSE
